django_zendesk_tickets-0.20.dist-info/licenses/LICENSE.txt
zendesk_tickets/__init__.py
zendesk_tickets/client.py
zendesk_tickets/forms.py
zendesk_tickets/views.py
zendesk_tickets/locale/cy/LC_MESSAGES/django.mo
zendesk_tickets/locale/cy/LC_MESSAGES/django.po
zendesk_tickets/locale/en_GB/LC_MESSAGES/django.mo
zendesk_tickets/locale/en_GB/LC_MESSAGES/django.po
zendesk_tickets/templates/zendesk_tickets/ticket.txt
django_zendesk_tickets-0.20.dist-info/METADATA
django_zendesk_tickets-0.20.dist-info/WHEEL
django_zendesk_tickets-0.20.dist-info/top_level.txt
django_zendesk_tickets-0.20.dist-info/RECORD
