Metadata-Version: 2.4
Name: django-zendesk-tickets
Version: 0.20
Summary: Django views and forms that submit tickets to Zendesk
Home-page: https://github.com/ministryofjustice/django-zendesk-tickets
Author: Ministry of Justice Digital & Technology
Author-email: dev@digital.justice.gov.uk
License: MIT
Keywords: django,tickets,zendesk
Classifier: Development Status :: 4 - Beta
Classifier: Framework :: Django
Classifier: Framework :: Django :: 4.2
Classifier: Framework :: Django :: 5.1
Classifier: Framework :: Django :: 5.2
Classifier: Intended Audience :: Developers
Classifier: License :: OSI Approved :: MIT License
Classifier: Natural Language :: English
Classifier: Operating System :: OS Independent
Classifier: Programming Language :: Python :: 3
Classifier: Programming Language :: Python :: 3 :: Only
Classifier: Programming Language :: Python :: 3.10
Classifier: Programming Language :: Python :: 3.11
Classifier: Programming Language :: Python :: 3.12
Classifier: Programming Language :: Python :: 3.13
Classifier: Programming Language :: Python :: 3.14
Requires-Python: >=3.6
License-File: LICENSE.txt
Requires-Dist: Django>=4.0
Requires-Dist: requests
Dynamic: license-file
